{
  "kpis": {
    "receita_total": 18871044.44,
    "qtd_pedidos": 12993,
    "ticket_medio": 1452.4,
    "clientes_ativos": 3581,
    "mom": -32.11,
    "vip": 904,
    "em_risco": 964,
    "pct_omni": 8.2,
    "vendedores": 20
  },
  "serie_real": [
    {
      "ano_mes": "2021-11",
      "receita_total": 302118.7
    },
    {
      "ano_mes": "2021-12",
      "receita_total": 223524.55
    },
    {
      "ano_mes": "2022-01",
      "receita_total": 280425.4
    },
    {
      "ano_mes": "2022-02",
      "receita_total": 254731.35
    },
    {
      "ano_mes": "2022-03",
      "receita_total": 460060.7
    },
    {
      "ano_mes": "2022-04",
      "receita_total": 390726.23
    },
    {
      "ano_mes": "2022-05",
      "receita_total": 545946.86
    },
    {
      "ano_mes": "2022-06",
      "receita_total": 501350.2
    },
    {
      "ano_mes": "2022-07",
      "receita_total": 338783.2
    },
    {
      "ano_mes": "2022-08",
      "receita_total": 354613.28
    },
    {
      "ano_mes": "2022-09",
      "receita_total": 260754.62
    },
    {
      "ano_mes": "2022-10",
      "receita_total": 194784.36
    },
    {
      "ano_mes": "2022-11",
      "receita_total": 258053.28
    },
    {
      "ano_mes": "2022-12",
      "receita_total": 170676.78
    },
    {
      "ano_mes": "2023-01",
      "receita_total": 125904.53
    },
    {
      "ano_mes": "2023-02",
      "receita_total": 137079.13
    },
    {
      "ano_mes": "2023-03",
      "receita_total": 6052.7
    },
    {
      "ano_mes": "2023-04",
      "receita_total": 6662.28
    },
    {
      "ano_mes": "2023-05",
      "receita_total": 4611.0
    },
    {
      "ano_mes": "2023-06",
      "receita_total": 1668.8
    },
    {
      "ano_mes": "2023-08",
      "receita_total": 6624.1
    },
    {
      "ano_mes": "2023-10",
      "receita_total": 2156.6
    },
    {
      "ano_mes": "2023-11",
      "receita_total": 2167.7
    },
    {
      "ano_mes": "2023-12",
      "receita_total": 1378.6
    },
    {
      "ano_mes": "2024-01",
      "receita_total": 217671.79
    },
    {
      "ano_mes": "2024-02",
      "receita_total": 310935.58
    },
    {
      "ano_mes": "2024-03",
      "receita_total": 315049.33
    },
    {
      "ano_mes": "2024-04",
      "receita_total": 364827.01
    },
    {
      "ano_mes": "2024-05",
      "receita_total": 257177.44
    },
    {
      "ano_mes": "2024-06",
      "receita_total": 273444.98
    },
    {
      "ano_mes": "2024-07",
      "receita_total": 225816.83
    },
    {
      "ano_mes": "2024-08",
      "receita_total": 266970.44
    },
    {
      "ano_mes": "2024-09",
      "receita_total": 232904.58
    },
    {
      "ano_mes": "2024-10",
      "receita_total": 324263.87
    },
    {
      "ano_mes": "2024-11",
      "receita_total": 220153.85
    }
  ],
  "serie_prev": [
    {
      "ano_mes": "2024-11",
      "receita_total": 220153.85
    },
    {
      "ano_mes": "2024-10",
      "receita_total": 230283.54
    },
    {
      "ano_mes": "2024-11",
      "receita_total": 249643.95
    },
    {
      "ano_mes": "2024-12",
      "receita_total": 227497.72
    }
  ],
  "trimestre": [
    {
      "trimestre": "Q1/2017",
      "valor_pedido": 27507.4
    },
    {
      "trimestre": "Q1/2018",
      "valor_pedido": 688068.22
    },
    {
      "trimestre": "Q1/2019",
      "valor_pedido": 572813.33
    },
    {
      "trimestre": "Q1/2020",
      "valor_pedido": 346714.4
    },
    {
      "trimestre": "Q1/2021",
      "valor_pedido": 737284.35
    },
    {
      "trimestre": "Q1/2022",
      "valor_pedido": 995217.45
    },
    {
      "trimestre": "Q1/2023",
      "valor_pedido": 269036.36
    },
    {
      "trimestre": "Q1/2024",
      "valor_pedido": 843656.7
    },
    {
      "trimestre": "Q2/2017",
      "valor_pedido": 80607.8
    },
    {
      "trimestre": "Q2/2018",
      "valor_pedido": 532025.67
    },
    {
      "trimestre": "Q2/2019",
      "valor_pedido": 890723.03
    },
    {
      "trimestre": "Q2/2020",
      "valor_pedido": 1174174.9
    },
    {
      "trimestre": "Q2/2021",
      "valor_pedido": 754505.32
    },
    {
      "trimestre": "Q2/2022",
      "valor_pedido": 1438023.29
    },
    {
      "trimestre": "Q2/2023",
      "valor_pedido": 12942.08
    },
    {
      "trimestre": "Q2/2024",
      "valor_pedido": 895449.43
    },
    {
      "trimestre": "Q3/2017",
      "valor_pedido": 426460.04
    },
    {
      "trimestre": "Q3/2018",
      "valor_pedido": 705088.48
    },
    {
      "trimestre": "Q3/2019",
      "valor_pedido": 471208.47
    },
    {
      "trimestre": "Q3/2020",
      "valor_pedido": 704372.2
    },
    {
      "trimestre": "Q3/2021",
      "valor_pedido": 685565.85
    },
    {
      "trimestre": "Q3/2022",
      "valor_pedido": 954151.1
    },
    {
      "trimestre": "Q3/2023",
      "valor_pedido": 6624.1
    },
    {
      "trimestre": "Q3/2024",
      "valor_pedido": 725691.85
    },
    {
      "trimestre": "Q4/2016",
      "valor_pedido": 46993.29
    },
    {
      "trimestre": "Q4/2017",
      "valor_pedido": 373450.76
    },
    {
      "trimestre": "Q4/2018",
      "valor_pedido": 468972.76
    },
    {
      "trimestre": "Q4/2019",
      "valor_pedido": 493223.77
    },
    {
      "trimestre": "Q4/2020",
      "valor_pedido": 582675.6
    },
    {
      "trimestre": "Q4/2021",
      "valor_pedido": 794181.4
    },
    {
      "trimestre": "Q4/2022",
      "valor_pedido": 623514.42
    },
    {
      "trimestre": "Q4/2023",
      "valor_pedido": 5702.9
    },
    {
      "trimestre": "Q4/2024",
      "valor_pedido": 544417.72
    }
  ],
  "segmentos": [
    {
      "segmento": "VIP",
      "count": 904
    },
    {
      "segmento": "Inativo",
      "count": 826
    },
    {
      "segmento": "Novo Promissor",
      "count": 571
    },
    {
      "segmento": "Perdendo VIP",
      "count": 547
    },
    {
      "segmento": "Em Risco",
      "count": 417
    },
    {
      "segmento": "Regular",
      "count": 179
    },
    {
      "segmento": "Leal",
      "count": 137
    }
  ],
  "canal": [
    {
      "canal": "Showroom",
      "valor_pedido": 22618.99
    },
    {
      "canal": "Vestishop",
      "valor_pedido": 84135.17
    },
    {
      "canal": "Link Sem Preço",
      "valor_pedido": 107920.14
    },
    {
      "canal": "Site",
      "valor_pedido": 127413.26
    },
    {
      "canal": "Aplicativo",
      "valor_pedido": 510584.92
    },
    {
      "canal": "Link",
      "valor_pedido": 2152786.32
    },
    {
      "canal": "Loja",
      "valor_pedido": 15862258.94
    }
  ],
  "faixa": [
    {
      "faixa": "Até R$200",
      "qtd": 566
    },
    {
      "faixa": "R$201-500",
      "qtd": 1487
    },
    {
      "faixa": "R$501-1000",
      "qtd": 3669
    },
    {
      "faixa": "R$1001-2000",
      "qtd": 4649
    },
    {
      "faixa": "R$2001-5000",
      "qtd": 2350
    },
    {
      "faixa": "Acima R$5000",
      "qtd": 266
    }
  ],
  "cupom": [
    {
      "tipo": "Sem Cupom",
      "qtd": 5457
    },
    {
      "tipo": "Frete Grátis",
      "qtd": 1948
    },
    {
      "tipo": "Desconto",
      "qtd": 1948
    },
    {
      "tipo": "Cashback",
      "qtd": 1819
    },
    {
      "tipo": "Parceiro",
      "qtd": 1819
    }
  ],
  "vendedores_rank": [
    {
      "vendedor": "Integração",
      "total_vendas": 968.4
    },
    {
      "vendedor": "Daniel",
      "total_vendas": 1348.5
    },
    {
      "vendedor": "Natalia Issi",
      "total_vendas": 3020.6
    },
    {
      "vendedor": "Jessica",
      "total_vendas": 3588.67
    },
    {
      "vendedor": "Fabio",
      "total_vendas": 7040.44
    },
    {
      "vendedor": "Pamela",
      "total_vendas": 8232.1
    },
    {
      "vendedor": "Amanda",
      "total_vendas": 38914.09
    },
    {
      "vendedor": "Gugu",
      "total_vendas": 100874.88
    },
    {
      "vendedor": "Lucas",
      "total_vendas": 104164.89
    },
    {
      "vendedor": "Caixa",
      "total_vendas": 107771.42
    },
    {
      "vendedor": "Usuário De Teste",
      "total_vendas": 114726.09
    },
    {
      "vendedor": "Sandra",
      "total_vendas": 1004020.26
    },
    {
      "vendedor": "Danisio",
      "total_vendas": 1073525.14
    },
    {
      "vendedor": "Gabi",
      "total_vendas": 1221194.07
    },
    {
      "vendedor": "Natalia R.",
      "total_vendas": 1734279.8
    },
    {
      "vendedor": "Erika",
      "total_vendas": 1918510.94
    },
    {
      "vendedor": "Fanny",
      "total_vendas": 2394294.88
    },
    {
      "vendedor": "Natalia",
      "total_vendas": 2761515.21
    },
    {
      "vendedor": "Denize",
      "total_vendas": 3126567.79
    },
    {
      "vendedor": "Keli",
      "total_vendas": 3146486.27
    }
  ],
  "top5_evo": [
    {
      "ano_mes": "2024-01",
      "vendedor": "Denize",
      "valor_pedido": 54286.66
    },
    {
      "ano_mes": "2024-01",
      "vendedor": "Erika",
      "valor_pedido": 609.4
    },
    {
      "ano_mes": "2024-01",
      "vendedor": "Fanny",
      "valor_pedido": 20479.0
    },
    {
      "ano_mes": "2024-01",
      "vendedor": "Natalia",
      "valor_pedido": 40553.28
    },
    {
      "ano_mes": "2024-02",
      "vendedor": "Denize",
      "valor_pedido": 70385.34
    },
    {
      "ano_mes": "2024-02",
      "vendedor": "Fanny",
      "valor_pedido": 54722.84
    },
    {
      "ano_mes": "2024-02",
      "vendedor": "Natalia",
      "valor_pedido": 46309.35
    },
    {
      "ano_mes": "2024-03",
      "vendedor": "Denize",
      "valor_pedido": 37475.09
    },
    {
      "ano_mes": "2024-03",
      "vendedor": "Fanny",
      "valor_pedido": 46064.86
    },
    {
      "ano_mes": "2024-03",
      "vendedor": "Natalia",
      "valor_pedido": 71644.79
    },
    {
      "ano_mes": "2024-04",
      "vendedor": "Denize",
      "valor_pedido": 86475.61
    },
    {
      "ano_mes": "2024-04",
      "vendedor": "Fanny",
      "valor_pedido": 71931.18
    },
    {
      "ano_mes": "2024-04",
      "vendedor": "Natalia",
      "valor_pedido": 49640.41
    },
    {
      "ano_mes": "2024-05",
      "vendedor": "Denize",
      "valor_pedido": 70457.26
    },
    {
      "ano_mes": "2024-05",
      "vendedor": "Fanny",
      "valor_pedido": 37943.18
    },
    {
      "ano_mes": "2024-05",
      "vendedor": "Natalia",
      "valor_pedido": 36834.76
    },
    {
      "ano_mes": "2024-06",
      "vendedor": "Denize",
      "valor_pedido": 52009.41
    },
    {
      "ano_mes": "2024-06",
      "vendedor": "Fanny",
      "valor_pedido": 37132.44
    },
    {
      "ano_mes": "2024-06",
      "vendedor": "Natalia",
      "valor_pedido": 48329.5
    },
    {
      "ano_mes": "2024-07",
      "vendedor": "Denize",
      "valor_pedido": 60365.5
    },
    {
      "ano_mes": "2024-07",
      "vendedor": "Fanny",
      "valor_pedido": 23345.23
    },
    {
      "ano_mes": "2024-07",
      "vendedor": "Natalia",
      "valor_pedido": 43109.35
    },
    {
      "ano_mes": "2024-08",
      "vendedor": "Denize",
      "valor_pedido": 97642.22
    },
    {
      "ano_mes": "2024-08",
      "vendedor": "Fanny",
      "valor_pedido": 31042.64
    },
    {
      "ano_mes": "2024-08",
      "vendedor": "Natalia",
      "valor_pedido": 30535.81
    },
    {
      "ano_mes": "2024-09",
      "vendedor": "Denize",
      "valor_pedido": 61380.07
    },
    {
      "ano_mes": "2024-09",
      "vendedor": "Fanny",
      "valor_pedido": 52752.02
    },
    {
      "ano_mes": "2024-09",
      "vendedor": "Natalia",
      "valor_pedido": 29945.49
    },
    {
      "ano_mes": "2024-10",
      "vendedor": "Denize",
      "valor_pedido": 111768.47
    },
    {
      "ano_mes": "2024-10",
      "vendedor": "Fanny",
      "valor_pedido": 57946.14
    },
    {
      "ano_mes": "2024-10",
      "vendedor": "Natalia",
      "valor_pedido": 21837.12
    },
    {
      "ano_mes": "2024-11",
      "vendedor": "Denize",
      "valor_pedido": 56673.62
    },
    {
      "ano_mes": "2024-11",
      "vendedor": "Fanny",
      "valor_pedido": 34481.52
    },
    {
      "ano_mes": "2024-11",
      "vendedor": "Natalia",
      "valor_pedido": 38535.06
    }
  ],
  "top5_names": [
    "Keli",
    "Denize",
    "Natalia",
    "Fanny",
    "Erika"
  ],
  "top_clientes": [
    {
      "nome_cliente": "PIMENTA ROSA CAPAO BONITO LTDA - ME",
      "segmento": "VIP",
      "frequencia": 234.0,
      "monetario": 279436.52,
      "ticket_medio": 1194.17
    },
    {
      "nome_cliente": "DEBORA SOUZA PRADO",
      "segmento": "VIP",
      "frequencia": 164.0,
      "monetario": 263556.98,
      "ticket_medio": 1607.05
    },
    {
      "nome_cliente": "BRUNA DE ANDRADE ESTEVES",
      "segmento": "VIP",
      "frequencia": 128.0,
      "monetario": 183842.01,
      "ticket_medio": 1436.27
    },
    {
      "nome_cliente": "P. M. G. DE TOLEDO",
      "segmento": "VIP",
      "frequencia": 104.0,
      "monetario": 145617.21,
      "ticket_medio": 1400.17
    },
    {
      "nome_cliente": "BRITO & CECCATTO LTDA - ME",
      "segmento": "VIP",
      "frequencia": 31.0,
      "monetario": 145447.55,
      "ticket_medio": 4691.86
    },
    {
      "nome_cliente": "CONCEICAO APARECIDA VALENTE DE CAMPOS - ME",
      "segmento": "VIP",
      "frequencia": 55.0,
      "monetario": 127963.38,
      "ticket_medio": 2326.61
    },
    {
      "nome_cliente": "CAMILA FERRAZ DE ANDRADE",
      "segmento": "VIP",
      "frequencia": 89.0,
      "monetario": 119695.8,
      "ticket_medio": 1344.9
    },
    {
      "nome_cliente": "SIRLEIS FERREIRA COUTINHO",
      "segmento": "VIP",
      "frequencia": 54.0,
      "monetario": 119059.7,
      "ticket_medio": 2204.81
    },
    {
      "nome_cliente": "New Concept",
      "segmento": "VIP",
      "frequencia": 3.0,
      "monetario": 100460.92,
      "ticket_medio": 33486.97
    },
    {
      "nome_cliente": "MARIANA LEOZ FRAILE CRIVELLARI",
      "segmento": "VIP",
      "frequencia": 49.0,
      "monetario": 96015.33,
      "ticket_medio": 1959.5
    }
  ],
  "previsao": [
    {
      "mes": "2024-10",
      "receita_prevista": 230283.54,
      "receita_min": 18862.86,
      "receita_max": 441704.22,
      "pedidos_previstos": 167
    },
    {
      "mes": "2024-11",
      "receita_prevista": 249643.95,
      "receita_min": -28968.21,
      "receita_max": 528256.1,
      "pedidos_previstos": 181
    },
    {
      "mes": "2024-12",
      "receita_prevista": 227497.72,
      "receita_min": -115353.55,
      "receita_max": 570348.98,
      "pedidos_previstos": 165
    }
  ],
  "modelos": [
    {
      "modelo": "SARIMA",
      "MAE": 41378,
      "RMSE": 54636,
      "MAPE_%": 16.1
    },
    {
      "modelo": "Holt-Winters",
      "MAE": 29149,
      "RMSE": 39067,
      "MAPE_%": 10.7
    },
    {
      "modelo": "Regressão Linear",
      "MAE": 31634,
      "RMSE": 36159,
      "MAPE_%": 12.2
    }
  ],
  "scatter": [
    {
      "vendedor": "Keli",
      "qtd_pedidos": 2038,
      "ticket_medio": 1543.91,
      "total_vendas": 3146486.27
    },
    {
      "vendedor": "Denize",
      "qtd_pedidos": 2054,
      "ticket_medio": 1522.18,
      "total_vendas": 3126567.79
    },
    {
      "vendedor": "Natalia",
      "qtd_pedidos": 2030,
      "ticket_medio": 1360.35,
      "total_vendas": 2761515.21
    },
    {
      "vendedor": "Fanny",
      "qtd_pedidos": 1693,
      "ticket_medio": 1414.23,
      "total_vendas": 2394294.88
    },
    {
      "vendedor": "Erika",
      "qtd_pedidos": 1439,
      "ticket_medio": 1333.23,
      "total_vendas": 1918510.94
    },
    {
      "vendedor": "Natalia R.",
      "qtd_pedidos": 1094,
      "ticket_medio": 1585.26,
      "total_vendas": 1734279.8
    },
    {
      "vendedor": "Gabi",
      "qtd_pedidos": 820,
      "ticket_medio": 1489.26,
      "total_vendas": 1221194.07
    },
    {
      "vendedor": "Danisio",
      "qtd_pedidos": 666,
      "ticket_medio": 1611.9,
      "total_vendas": 1073525.14
    },
    {
      "vendedor": "Sandra",
      "qtd_pedidos": 739,
      "ticket_medio": 1358.62,
      "total_vendas": 1004020.26
    },
    {
      "vendedor": "Usuário De Teste",
      "qtd_pedidos": 73,
      "ticket_medio": 1571.59,
      "total_vendas": 114726.09
    },
    {
      "vendedor": "Caixa",
      "qtd_pedidos": 123,
      "ticket_medio": 876.19,
      "total_vendas": 107771.42
    },
    {
      "vendedor": "Lucas",
      "qtd_pedidos": 58,
      "ticket_medio": 1795.95,
      "total_vendas": 104164.89
    },
    {
      "vendedor": "Gugu",
      "qtd_pedidos": 92,
      "ticket_medio": 1096.47,
      "total_vendas": 100874.88
    },
    {
      "vendedor": "Amanda",
      "qtd_pedidos": 46,
      "ticket_medio": 845.96,
      "total_vendas": 38914.09
    },
    {
      "vendedor": "Pamela",
      "qtd_pedidos": 8,
      "ticket_medio": 1029.01,
      "total_vendas": 8232.1
    },
    {
      "vendedor": "Fabio",
      "qtd_pedidos": 14,
      "ticket_medio": 502.89,
      "total_vendas": 7040.44
    },
    {
      "vendedor": "Jessica",
      "qtd_pedidos": 3,
      "ticket_medio": 1196.22,
      "total_vendas": 3588.67
    },
    {
      "vendedor": "Natalia Issi",
      "qtd_pedidos": 1,
      "ticket_medio": 3020.6,
      "total_vendas": 3020.6
    },
    {
      "vendedor": "Daniel",
      "qtd_pedidos": 1,
      "ticket_medio": 1348.5,
      "total_vendas": 1348.5
    },
    {
      "vendedor": "Integração",
      "qtd_pedidos": 1,
      "ticket_medio": 968.4,
      "total_vendas": 968.4
    }
  ],
  "dim_vend_all": [
    {
      "vendedor": "Keli",
      "total_vendas": 3146486.27,
      "qtd_pedidos": 2038,
      "ticket_medio": 1543.91,
      "clientes_atendidos": 405,
      "pedidos_por_cliente": 5.03
    },
    {
      "vendedor": "Denize",
      "total_vendas": 3126567.79,
      "qtd_pedidos": 2054,
      "ticket_medio": 1522.18,
      "clientes_atendidos": 404,
      "pedidos_por_cliente": 5.08
    },
    {
      "vendedor": "Natalia",
      "total_vendas": 2761515.21,
      "qtd_pedidos": 2030,
      "ticket_medio": 1360.35,
      "clientes_atendidos": 688,
      "pedidos_por_cliente": 2.95
    },
    {
      "vendedor": "Fanny",
      "total_vendas": 2394294.88,
      "qtd_pedidos": 1693,
      "ticket_medio": 1414.23,
      "clientes_atendidos": 605,
      "pedidos_por_cliente": 2.8
    },
    {
      "vendedor": "Erika",
      "total_vendas": 1918510.94,
      "qtd_pedidos": 1439,
      "ticket_medio": 1333.23,
      "clientes_atendidos": 424,
      "pedidos_por_cliente": 3.39
    },
    {
      "vendedor": "Natalia R.",
      "total_vendas": 1734279.8,
      "qtd_pedidos": 1094,
      "ticket_medio": 1585.26,
      "clientes_atendidos": 515,
      "pedidos_por_cliente": 2.12
    },
    {
      "vendedor": "Gabi",
      "total_vendas": 1221194.07,
      "qtd_pedidos": 820,
      "ticket_medio": 1489.26,
      "clientes_atendidos": 346,
      "pedidos_por_cliente": 2.37
    },
    {
      "vendedor": "Danisio",
      "total_vendas": 1073525.14,
      "qtd_pedidos": 666,
      "ticket_medio": 1611.9,
      "clientes_atendidos": 240,
      "pedidos_por_cliente": 2.78
    },
    {
      "vendedor": "Sandra",
      "total_vendas": 1004020.26,
      "qtd_pedidos": 739,
      "ticket_medio": 1358.62,
      "clientes_atendidos": 451,
      "pedidos_por_cliente": 1.64
    },
    {
      "vendedor": "Usuário De Teste",
      "total_vendas": 114726.09,
      "qtd_pedidos": 73,
      "ticket_medio": 1571.59,
      "clientes_atendidos": 45,
      "pedidos_por_cliente": 1.62
    },
    {
      "vendedor": "Caixa",
      "total_vendas": 107771.42,
      "qtd_pedidos": 123,
      "ticket_medio": 876.19,
      "clientes_atendidos": 94,
      "pedidos_por_cliente": 1.31
    },
    {
      "vendedor": "Lucas",
      "total_vendas": 104164.89,
      "qtd_pedidos": 58,
      "ticket_medio": 1795.95,
      "clientes_atendidos": 44,
      "pedidos_por_cliente": 1.32
    },
    {
      "vendedor": "Gugu",
      "total_vendas": 100874.88,
      "qtd_pedidos": 92,
      "ticket_medio": 1096.47,
      "clientes_atendidos": 75,
      "pedidos_por_cliente": 1.23
    },
    {
      "vendedor": "Amanda",
      "total_vendas": 38914.09,
      "qtd_pedidos": 46,
      "ticket_medio": 845.96,
      "clientes_atendidos": 22,
      "pedidos_por_cliente": 2.09
    },
    {
      "vendedor": "Pamela",
      "total_vendas": 8232.1,
      "qtd_pedidos": 8,
      "ticket_medio": 1029.01,
      "clientes_atendidos": 8,
      "pedidos_por_cliente": 1.0
    },
    {
      "vendedor": "Fabio",
      "total_vendas": 7040.44,
      "qtd_pedidos": 14,
      "ticket_medio": 502.89,
      "clientes_atendidos": 2,
      "pedidos_por_cliente": 7.0
    },
    {
      "vendedor": "Jessica",
      "total_vendas": 3588.67,
      "qtd_pedidos": 3,
      "ticket_medio": 1196.22,
      "clientes_atendidos": 3,
      "pedidos_por_cliente": 1.0
    },
    {
      "vendedor": "Natalia Issi",
      "total_vendas": 3020.6,
      "qtd_pedidos": 1,
      "ticket_medio": 3020.6,
      "clientes_atendidos": 1,
      "pedidos_por_cliente": 1.0
    },
    {
      "vendedor": "Daniel",
      "total_vendas": 1348.5,
      "qtd_pedidos": 1,
      "ticket_medio": 1348.5,
      "clientes_atendidos": 1,
      "pedidos_por_cliente": 1.0
    },
    {
      "vendedor": "Integração",
      "total_vendas": 968.4,
      "qtd_pedidos": 1,
      "ticket_medio": 968.4,
      "clientes_atendidos": 1,
      "pedidos_por_cliente": 1.0
    }
  ]
}